FP8/M=4, N=9(and implementation)/INT MAC/int_mac_9.v
// ============================================================
// Full Integer MAC -- M=4, N=K=9  (Sign-After-Multiply version)
//
// Key difference from original:
//   Mantissas are received as 4-bit UNSIGNED [0..15].
//   A separate sign_flat bus carries one XOR-sign bit per lane.
//   Multiplication is done unsigned, sign is applied AFTER
//   the product -- exactly like the FP8 MLB pos/neg mask approach.
//   This eliminates the >>1 truncation that cost 1 bit of precision.
//
// Block 1 : 9 parallel unsigned MAC lanes
//           product_i = a_i * b_i          (4bx4b -> 8b unsigned)
//           signed_product_i = sign_i ? -product_i : +product_i  (9b signed)
//           acc_i += signed_product_i       (11b signed, handles M=4)
//
// Block 2 : Reduction tree 9 -> 1         (14-bit signed result)
//
// Block 3 : Scaling + offset
//           result = ax*aw*s_final + bxw
//
// Ports
//   clk      -- clock
//   rst      -- synchronous reset
//   load     -- hold high for M cycles to accumulate M dot-product slices
//   a_flat   -- 9 x 4-bit UNSIGNED activations (36-bit bus)
//   b_flat   -- 9 x 4-bit UNSIGNED weights     (36-bit bus)
//   sign_flat-- 9 x 1-bit product sign         (sign_x XOR sign_w)
//   alpha_x  -- unsigned 4-bit scaling factor ax
//   alpha_w  -- unsigned 4-bit scaling factor aw
//   beta_xw  -- signed 8-bit offset bxw
//   result   -- 21-bit signed dot(x^q, w^q)
// ============================================================

module int_mac_9 (
    input clk,
    input rst,
    input load,

    input [35:0] a_flat,    // 9 x 4-bit UNSIGNED activations
    input [35:0] b_flat,    // 9 x 4-bit UNSIGNED weights
    input [8:0]  sign_flat, // 9 x 1-bit product sign (sign_x XOR sign_w)

    input [3:0]        alpha_x,
    input [3:0]        alpha_w,
    input signed [7:0] beta_xw,

    output signed [20:0] result
);

// ============================================================
// BLOCK 1 -- 9 parallel unsigned Multiply + sign + Accumulate
//
// product_i        : 4b x 4b unsigned -> 8-bit unsigned  (max 225)
// signed_product_i : +/-product_i     -> 9-bit signed    (+/-225)
// acc_i            : sum signed_products -> 11-bit signed  (M=4: max +/-900)
// ============================================================

wire [7:0]         product       [0:8]; // unsigned magnitude product
wire signed [8:0]  signed_product[0:8]; // sign applied after multiply
reg  signed [10:0] acc           [0:8]; // accumulator, 11-bit for M=4

genvar i;
generate
    for (i = 0; i < 9; i = i + 1) begin : gen_mac_lane

        // Unsigned 4-bit x 4-bit multiply (no precision loss)
        assign product[i] = a_flat[4*i +: 4] * b_flat[4*i +: 4];

        // Apply sign AFTER multiply: negative if sign_x XOR sign_w = 1
        assign signed_product[i] = sign_flat[i]
                                    ? -$signed({1'b0, product[i]})
                                    :  $signed({1'b0, product[i]});

        // Accumulate (sign-extend 9-bit -> 11-bit before adding)
        always @(posedge clk) begin
            if (rst)
                acc[i] <= 11'sd0;
            else if (load)
                acc[i] <= acc[i] + {{2{signed_product[i][8]}}, signed_product[i]};
        end

    end
endgenerate

// ============================================================
// BLOCK 2 -- Reduction tree 9 -> 1
// acc = 11-bit signed, each level adds 1 guard bit
// ============================================================

    wire signed [11:0] s1 [0:3];
    wire signed [12:0] s2 [0:1];

    genvar j;
    generate
        for (j = 0; j < 4; j = j + 1) begin : gen_r1
            assign s1[j] = $signed(acc[2*j]) + $signed(acc[2*j+1]);
        end
        for (j = 0; j < 2; j = j + 1) begin : gen_r2
            assign s2[j] = $signed(s1[2*j]) + $signed(s1[2*j+1]);
        end
    endgenerate

wire signed [13:0] s_final;
assign s_final = $signed(s2[0]) + $signed(s2[1]) + $signed({{{3{{acc[8][10]}}}}, acc[8]});

// ============================================================
// BLOCK 3 -- Scaling ax*aw x sum + offset bxw
// ax, aw  : unsigned 4-bit -> product 8-bit unsigned
// s_final : signed 14-bit
// scaled  : 23-bit (truncated to 21)
// ============================================================

wire [7:0]        alpha_prod;   // ax x aw (unsigned 8-bit)
wire signed [8:0] alpha_prod_s; // zero-extended to signed
wire signed [22:0] scaled;

assign alpha_prod   = alpha_x * alpha_w;
assign alpha_prod_s = {1'b0, alpha_prod};
assign scaled       = $signed(s_final) * $signed(alpha_prod_s);

assign result = scaled[20:0] + {{13{beta_xw[7]}}, beta_xw};

endmodule

FP8/M=4, N=9(and implementation)/bpf_aligner.v
module bfp_aligner (
    input  [71:0] fp8_vec,
    output reg [35:0] aligned_planes, // Reorganized for MLB_4 axi/awi ports
    output reg [3:0]   max_exp
);
    reg [3:0] exps [0:8];
    reg [3:0] mants [0:8];
    reg [3:0] shift_amt;
    reg [3:0] shifted_mant;
    integer i;

    always @(*) begin
        max_exp = 4'd0;
        
        // Phase 1: Extract Exponents and Find Max
        for (i=0; i<9; i=i+1) begin
            exps[i] = fp8_vec[(i*8)+3 +: 4];
            if (exps[i] > max_exp) begin
                max_exp = exps[i];
            end
        end

        // Phase 2: Align Mantissas and "Corner Turn" into Bit Planes
        for (i=0; i<9; i=i+1) begin
            // Extract mantissa and add hidden '1'
            if (exps[i] != 4'd0) begin
                mants[i] = {1'b1, fp8_vec[(i*8) +: 3]};
            end else begin
                mants[i] = 4'd0; // Flush subnormals to zero
            end

            // Right shift to align to the block max exponent
            shift_amt = max_exp - exps[i];
            shifted_mant = mants[i] >> shift_amt;

            // CORNER TURN: Map the 4-bit integer into the 4 planes for MLB_4
            aligned_planes[i]         = shifted_mant[0]; // Plane 0 (axi[8:0])
            aligned_planes[9 + i]  = shifted_mant[1]; // Plane 1 (axi[17:9])
            aligned_planes[18 + i] = shifted_mant[2]; // Plane 2 (axi[26:18])
            aligned_planes[27 + i] = shifted_mant[3]; // Plane 3 (axi[35:27])
        end
    end
endmodule

FP8/M=4, N=9(and implementation)/INT MAC/fp8_int_top.v
module fp8_int_top (
    input  clk,
    input  rst,
    input  valid_in, // Connects to 'load' on the MAC array
    input  [71:0] fp8_activations,
    input  [71:0] fp8_weights,
    output signed [20:0] wide_integer_sum,
    output signed [8:0]   shared_exponent
);

    // ---------------- BFP alignment (Reused from MLB design) ----------------
    wire [35:0] axi_planes;
    wire [35:0] awi_planes;
    wire [3:0]   max_exp_x;
    wire [3:0]   max_exp_w;

    bfp_aligner align_x (
        .fp8_vec(fp8_activations),
        .aligned_planes(axi_planes),
        .max_exp(max_exp_x)
    );

    bfp_aligner align_w (
        .fp8_vec(fp8_weights),
        .aligned_planes(awi_planes),
        .max_exp(max_exp_w)
    );

    // ---------------- Format for INT MAC (Plane-to-Flat, Sign Separate) ----------------
    // Mantissas stay UNSIGNED [0..15]. Sign is handled AFTER multiplication inside int_mac_9,
    // exactly like the FP8 MLB design -- avoids the >>1 truncation of the old approach.
    reg [3:0]  a_flat_reg  [0:8]; // 4-bit unsigned mantissa per lane
    reg [3:0]  b_flat_reg  [0:8]; // 4-bit unsigned mantissa per lane
    reg [8:0] sign_flat_reg;      // product sign per lane: sign_x XOR sign_w

    wire [35:0] a_flat_wire;
    wire [35:0] b_flat_wire;

    integer i;
    reg [3:0] mant_x, mant_w;

    always @(*) begin
        for (i = 0; i < 9; i = i + 1) begin
            // 1. Reconstruct full 4-bit unsigned mantissa from BFP bit-planes
            mant_x = {axi_planes[27+i], axi_planes[18+i], axi_planes[9+i], axi_planes[i]};
            mant_w = {awi_planes[27+i], awi_planes[18+i], awi_planes[9+i], awi_planes[i]};

            a_flat_reg[i] = mant_x;
            b_flat_reg[i] = mant_w;

            // 2. Compute product sign (sign-magnitude rule: sign = XOR of input signs)
            sign_flat_reg[i] = fp8_activations[i*8 + 7] ^ fp8_weights[i*8 + 7];
        end
    end

    // Pack mantissa registers into flat buses
    genvar k;
    generate
        for (k = 0; k < 9; k = k + 1) begin : pack_flat
            assign a_flat_wire[4*k +: 4] = a_flat_reg[k];
            assign b_flat_wire[4*k +: 4] = b_flat_reg[k];
        end
    endgenerate

    // ---------------- INT MAC Instantiation ----------------
    int_mac_9 mac_array (
        .clk(clk),
        .rst(rst),
        .load(valid_in),
        .a_flat(a_flat_wire),
        .b_flat(b_flat_wire),
        .sign_flat(sign_flat_reg),   // per-lane product sign
        .alpha_x(4'd1),
        .alpha_w(4'd1),
        .beta_xw(8'sd0),
        .result(wide_integer_sum)
    );

    // ---------------- Final Exponent ----------------
    // No >>1 compensation needed anymore. Full 4-bit mantissas are used (hidden bit at
    // position 3, so each mantissa integer is 2^3 = 8x the true fraction).
    // Two mantissas multiplied -> 2^6 total scale -> same formula as FP8 MLB: bias*2 + 6 = 14+6 = 20
    assign shared_exponent = $signed({5'b0, max_exp_x}) + $signed({5'b0, max_exp_w}) - 9'sd20;

endmodule

FP8/M=4, N=9(and implementation)/INT MAC/tb_FP8.v
`timescale 1ns/1ps

module tb_fp8_int_top;

    // ------------------------------------------------------------------
    // DUT signals
    // ------------------------------------------------------------------
    reg  clk, rst, valid_in;
    reg  [71:0] fp8_activations, fp8_weights;
    wire signed [20:0] wide_integer_sum;
    wire signed [8:0]   shared_exponent;

    integer pass_count = 0;
    integer fail_count = 0;
    integer test_num   = 0;

    // Instantiate the INT MAC top-level wrapper
    fp8_int_top dut (
        .clk(clk),
        .rst(rst),
        .valid_in(valid_in),
        .fp8_activations(fp8_activations),
        .fp8_weights(fp8_weights),
        .wide_integer_sum(wide_integer_sum),
        .shared_exponent(shared_exponent)
    );

    // ------------------------------------------------------------------
    // Clock
    // ------------------------------------------------------------------
    initial clk = 1'b0;
    always #5 clk = ~clk;

    // ------------------------------------------------------------------
    // Per-lane stimulus storage
    // ------------------------------------------------------------------
    reg [7:0] act_lane [0:8];
    reg [7:0] wt_lane  [0:8];

    // ------------------------------------------------------------------
    // Waveform dump
    // ------------------------------------------------------------------
    initial begin
        $dumpfile("int_mac_sim.vcd");
        $dumpvars(0, tb_fp8_int_top);
    end

    // ------------------------------------------------------------------
    // Random FP8 (E4M3) lane generator
    // ------------------------------------------------------------------
    function [7:0] rand_fp8(input allow_zero);
        reg [31:0] r1, r2, r3;
        reg [3:0]  exp_f;
        begin
            r1 = $random;
            r2 = $random;
            r3 = $random;
            if (allow_zero)
                exp_f = r1 % 16;
            else
                exp_f = (r1 % 15) + 1;
            rand_fp8 = {r2[0], exp_f, r3[2:0]};
        end
    endfunction

    // ------------------------------------------------------------------
    // Helpers to build directed stimulus
    // ------------------------------------------------------------------
    task clear_all_lanes;
        integer i;
        begin
            for (i = 0; i < 9; i = i + 1) begin
                act_lane[i] = 8'b0;
                wt_lane[i]  = 8'b0;
            end
        end
    endtask

task set_lane(input integer is_weight, input integer idx, input sign, input [3:0] exp_f, input [2:0] mant_f);
        begin
            if (is_weight)
                wt_lane[idx] = {sign, exp_f, mant_f};
            else
                act_lane[idx] = {sign, exp_f, mant_f};
        end
    endtask

task fill_random_lanes(input allow_zero);
        integer i;
        begin
            for (i = 0; i < 9; i = i + 1) begin
                act_lane[i] = rand_fp8(allow_zero);
                wt_lane[i]  = rand_fp8(allow_zero);
            end
        end
    endtask

task pack_vectors;
        integer i;
        begin
            for (i = 0; i < 9; i = i + 1) begin
                fp8_activations[i*8 +: 8] = act_lane[i];
                fp8_weights[i*8 +: 8]     = wt_lane[i];
            end
        end
    endtask

    // ------------------------------------------------------------------
    // Behavioral reference model (UPDATED: sign-after-multiply, no >>1 truncation)
    // ------------------------------------------------------------------
task compute_reference(output reg signed [20:0] ref_result,
                           output reg [8:0]         ref_exponent);
        integer i;
        reg sx, sw;
        reg [3:0] ex, ew;
        reg [3:0] mx, mw;
        reg [3:0] max_ex, max_ew;
        integer shift_x, shift_w;
        reg [3:0] smx, smw;
        
        integer prod;
        integer total_sum;
        begin
            max_ex = 4'd0;
            max_ew = 4'd0;
            for (i = 0; i < 9; i = i + 1) begin
                ex = act_lane[i][6:3];
                ew = wt_lane[i][6:3];
                if (ex > max_ex) max_ex = ex;
                if (ew > max_ew) max_ew = ew;
            end

            total_sum = 0;
            for (i = 0; i < 9; i = i + 1) begin
                sx = act_lane[i][7];
                ex = act_lane[i][6:3];
                mx = (ex != 4'd0) ? {1'b1, act_lane[i][2:0]} : 4'd0;

                sw = wt_lane[i][7];
                ew = wt_lane[i][6:3];
                mw = (ew != 4'd0) ? {1'b1, wt_lane[i][2:0]} : 4'd0;

                shift_x = max_ex - ex;
                shift_w = max_ew - ew;

                smx = mx >> shift_x;
                smw = mw >> shift_w;

                // Full mantissa magnitude used -- no >>1 truncation
                // Sign applied AFTER product (XOR rule), matching new int_mac_9
                prod = smx * smw;
                if (sx ^ sw)
                    total_sum = total_sum - prod;
                else
                    total_sum = total_sum + prod;
            end

            ref_result   = total_sum;
            // No >>1 compensation: same formula as FP8 MLB (14 bias + 6 mantissa scale = 20)
            ref_exponent = $signed({5'b0, max_ex}) + $signed({5'b0, max_ew}) - 9'sd20;
        end
    endtask

    // ------------------------------------------------------------------
    // Apply and Check
    // ------------------------------------------------------------------
task apply_and_check(input [8*40-1:0] name);
        reg signed [20:0] expected_result;
        reg [8:0]         expected_exponent;
        begin
            test_num = test_num + 1;
            pack_vectors;
            compute_reference(expected_result, expected_exponent);

            // 1. Clear the Accumulators in the MAC array
            @(negedge clk);
            rst = 1'b1;
            
            // 2. Release reset and load data
            @(negedge clk);
            rst = 1'b0;
            valid_in = 1'b1;
            
            // 3. Stop loading (let reduction tree combinational logic settle)
            @(negedge clk);
            valid_in = 1'b0;

            // 4. Verify results immediately (Tree adder is combinational off the acc)
            if ((wide_integer_sum !== expected_result) ||
                (shared_exponent !== expected_exponent)) begin
                $display("[TEST %0d] %-0s : FAIL", test_num, name);
                $display("           expected : sum=%0d  exp=%0d", expected_result, expected_exponent);
                $display("           got      : sum=%0d  exp=%0d", wide_integer_sum, shared_exponent);
                fail_count = fail_count + 1;
            end
            else begin
                $display("[TEST %0d] %-0s : PASS  (sum=%0d, exp=%0d)", test_num, name, wide_integer_sum, shared_exponent);
                pass_count = pass_count + 1;
            end

            @(posedge clk);
        end
    endtask

    // ------------------------------------------------------------------
    // Main stimulus
    // ------------------------------------------------------------------
    integer t;
    integer i;
    initial begin
        rst      = 1'b1;
        valid_in = 1'b0;
        fp8_activations = 72'b0;
        fp8_weights     = 72'b0;
        clear_all_lanes;

        repeat (3) @(posedge clk);
        rst = 1'b0;
        @(posedge clk);

        // ---------------- Directed corner cases ----------------
        clear_all_lanes;
        apply_and_check("All zeros");

        for (i = 0; i < 9; i = i + 1) begin
            set_lane(0, i, 1'b0, 4'd7, 3'b000);
            set_lane(1, i, 1'b0, 4'd7, 3'b000);
        end
        apply_and_check("All positive equal value");

        for (i = 0; i < 9; i = i + 1) begin
            set_lane(0, i, 1'b0, 4'd7, 3'b000);
            set_lane(1, i, 1'b1, 4'd7, 3'b000);
        end
        apply_and_check("All positive act, all negative weight");

        for (i = 0; i < 9; i = i + 1) begin
            set_lane(0, i, 1'b1, 4'd7, 3'b011);
            set_lane(1, i, 1'b1, 4'd7, 3'b011);
        end
        apply_and_check("Both negative (signs cancel)");

        for (i = 0; i < 9; i = i + 1) begin
            set_lane(0, i, i[0], 4'd9, 3'b010);
            set_lane(1, i, 1'b0,  4'd9, 3'b101);
        end
        apply_and_check("Alternating activation sign");

        for (i = 0; i < 9; i = i + 1) begin
            set_lane(0, i, 1'b0, 4'd15, 3'b111);
            set_lane(1, i, 1'b0, 4'd15, 3'b111);
        end
        apply_and_check("Max magnitude, all positive");

        for (i = 0; i < 9; i = i + 1) begin
            set_lane(0, i, i[0],  4'd15, 3'b111);
            set_lane(1, i, ~i[0], 4'd15, 3'b111);
        end
        apply_and_check("Max magnitude, alternating signs");

        for (i = 0; i < 9; i = i + 1) begin
            if (i[0]) begin
                set_lane(0, i, 1'b0, 4'd0, 3'b101);
                set_lane(1, i, 1'b0, 4'd0, 3'b011);
            end else begin
                set_lane(0, i, 1'b0, 4'd8, 3'b001);
                set_lane(1, i, 1'b0, 4'd8, 3'b001);
            end
        end
        apply_and_check("Subnormal flush (half lanes exp=0)");

        clear_all_lanes;
        set_lane(0, 0, 1'b0, 4'd10, 3'b110);
        set_lane(1, 0, 1'b1, 4'd10, 3'b110);
        apply_and_check("Single nonzero lane");

        clear_all_lanes;
        set_lane(0, 0, 1'b0, 4'd15, 3'b111);
        set_lane(1, 0, 1'b0, 4'd15, 3'b111);
        for (i = 1; i < 9; i = i + 1) begin
            set_lane(0, i, 1'b0, 4'd1, 3'b000);
            set_lane(1, i, 1'b0, 4'd1, 3'b000);
        end
        apply_and_check("Wide dynamic range (shift-to-zero stress)");

        for (i = 0; i < 9; i = i + 1) begin
            set_lane(0, i, 1'b0, 4'd0, 3'b111);
            set_lane(1, i, 1'b0, 4'd12, 3'b101);
        end
        apply_and_check("All activations flushed to zero");

        // ---------------- Randomized cases ----------------
        for (t = 0; t < 50; t = t + 1) begin
            if (t % 3 == 0)
                fill_random_lanes(1'b1);  // allow zero-exponent lanes
            else
                fill_random_lanes(1'b0);  // normal numbers only
            apply_and_check("Random test");
        end

        // =====================================================================
        // Final report
        // =====================================================================
        $display("\n======================================================");
        $display("  TEST SUMMARY: %0d PASSED,  %0d FAILED",
                  pass_count, fail_count);
        $display("======================================================");
        if (fail_count == 0)
            $display("  ALL TESTS PASSED");
        else
            $display("  *** FAILURES DETECTED -- check waveform in int_mac_sim.vcd ***");
        $display("");

        $finish;
    end

endmodule

FP8/M=4, N=9(and implementation)/INT MAC/int_mac_sim.vcd
$date
	Wed Jun 24 20:14:58 2026
$end
$version
	Icarus Verilog
$end
$timescale
	1ps
$end
$scope module tb_fp8_int_top $end
$var wire 21 ! wide_integer_sum [20:0] $end
$var wire 9 " shared_exponent [8:0] $end
$var reg 1 # clk $end
$var reg 72 $ fp8_activations [71:0] $end
$var reg 72 % fp8_weights [71:0] $end
$var reg 1 & rst $end
$var reg 1 ' valid_in $end
$var integer 32 ( fail_count [31:0] $end
$var integer 32 ) i [31:0] $end
$var integer 32 * pass_count [31:0] $end
$var integer 32 + t [31:0] $end
$var integer 32 , test_num [31:0] $end
$scope function rand_fp8 $end
$var reg 1 - allow_zero $end
$var reg 4 . exp_f [3:0] $end
$var reg 32 / r1 [31:0] $end
$var reg 32 0 r2 [31:0] $end
$var reg 32 1 r3 [31:0] $end
$upscope $end
$scope module dut $end
$var wire 1 # clk $end
$var wire 72 2 fp8_activations [71:0] $end
$var wire 72 3 fp8_weights [71:0] $end
$var wire 1 & rst $end
$var wire 1 ' valid_in $end
$var wire 21 4 wide_integer_sum [20:0] $end
$var wire 9 5 shared_exponent [8:0] $end
$var wire 4 6 max_exp_x [3:0] $end
$var wire 4 7 max_exp_w [3:0] $end
$var wire 36 8 b_flat_wire [35:0] $end
$var wire 36 9 axi_planes [35:0] $end
$var wire 36 : awi_planes [35:0] $end
$var wire 36 ; a_flat_wire [35:0] $end
$var reg 4 < mant_w [3:0] $end
$var reg 4 = mant_x [3:0] $end
$var reg 9 > sign_flat_reg [8:0] $end
$var integer 32 ? i [31:0] $end
$scope begin pack_flat[0] $end
$var parameter 2 @ k $end
$upscope $end
$scope begin pack_flat[1] $end
$var parameter 2 A k $end
$upscope $end
$scope begin pack_flat[2] $end
$var parameter 3 B k $end
$upscope $end
$scope begin pack_flat[3] $end
$var parameter 3 C k $end
$upscope $end
$scope begin pack_flat[4] $end
$var parameter 4 D k $end
$upscope $end
$scope begin pack_flat[5] $end
$var parameter 4 E k $end
$upscope $end
$scope begin pack_flat[6] $end
$var parameter 4 F k $end
$upscope $end
$scope begin pack_flat[7] $end
$var parameter 4 G k $end
$upscope $end
$scope begin pack_flat[8] $end
$var parameter 5 H k $end
$upscope $end
$scope module align_w $end
$var wire 72 I fp8_vec [71:0] $end
$var reg 36 J aligned_planes [35:0] $end
$var reg 4 K max_exp [3:0] $end
$var reg 4 L shift_amt [3:0] $end
$var reg 4 M shifted_mant [3:0] $end
$var integer 32 N i [31:0] $end
$upscope $end
$scope module align_x $end
$var wire 72 O fp8_vec [71:0] $end
$var reg 36 P aligned_planes [35:0] $end
$var reg 4 Q max_exp [3:0] $end
$var reg 4 R shift_amt [3:0] $end
$var reg 4 S shifted_mant [3:0] $end
$var integer 32 T i [31:0] $end
$upscope $end
$scope module mac_array $end
$var wire 36 U a_flat [35:0] $end
$var wire 4 V alpha_w [3:0] $end
$var wire 4 W alpha_x [3:0] $end
$var wire 36 X b_flat [35:0] $end
$var wire 8 Y beta_xw [7:0] $end
$var wire 1 # clk $end
$var wire 1 ' load $end
$var wire 1 & rst $end
$var wire 9 Z sign_flat [8:0] $end
$var wire 23 [ scaled [22:0] $end
$var wire 14 \ s_final [13:0] $end
$var wire 21 ] result [20:0] $end
$var wire 9 ^ alpha_prod_s [8:0] $end
$var wire 8 _ alpha_prod [7:0] $end
$scope begin gen_mac_lane[0] $end
$var parameter 2 ` i $end
$upscope $end
$scope begin gen_mac_lane[1] $end
$var parameter 2 a i $end
$upscope $end
$scope begin gen_mac_lane[2] $end
$var parameter 3 b i $end
$upscope $end
$scope begin gen_mac_lane[3] $end
$var parameter 3 c i $end
$upscope $end
$scope begin gen_mac_lane[4] $end
$var parameter 4 d i $end
$upscope $end
$scope begin gen_mac_lane[5] $end
$var parameter 4 e i $end
$upscope $end
$scope begin gen_mac_lane[6] $end
$var parameter 4 f i $end
$upscope $end
$scope begin gen_mac_lane[7] $end
$var parameter 4 g i $end
$upscope $end
$scope begin gen_mac_lane[8] $end
$var parameter 5 h i $end
$upscope $end
$scope begin gen_r1[0] $end
$var parameter 2 i j $end
$upscope $end
$scope begin gen_r1[1] $end
$var parameter 2 j j $end
$upscope $end
$scope begin gen_r1[2] $end
$var parameter 3 k j $end
$upscope $end
$scope begin gen_r1[3] $end
$var parameter 3 l j $end
$upscope $end
$scope begin gen_r2[0] $end
$var parameter 2 m j $end
$upscope $end
$scope begin gen_r2[1] $end
$var parameter 2 n j $end
$upscope $end
$upscope $end
$upscope $end
$scope task apply_and_check $end
$var reg 9 o expected_exponent [8:0] $end
$var reg 21 p expected_result [20:0] $end
$var reg 320 q name [319:0] $end
$upscope $end
$scope task clear_all_lanes $end
$var integer 32 r i [31:0] $end
$upscope $end
$scope task compute_reference $end
$var reg 4 s ew [3:0] $end
$var reg 4 t ex [3:0] $end
$var reg 4 u max_ew [3:0] $end
$var reg 4 v max_ex [3:0] $end
$var reg 4 w mw [3:0] $end
$var reg 4 x mx [3:0] $end
$var reg 9 y ref_exponent [8:0] $end
$var reg 21 z ref_result [20:0] $end
$var reg 4 { smw [3:0] $end
$var reg 4 | smx [3:0] $end
$var reg 1 } sw $end
$var reg 1 ~ sx $end
$var integer 32 !" i [31:0] $end
$var integer 32 "" prod [31:0] $end
$var integer 32 #" shift_w [31:0] $end
$var integer 32 $" shift_x [31:0] $end
$var integer 32 %" total_sum [31:0] $end
$upscope $end
$scope task fill_random_lanes $end
$var reg 1 &" allow_zero $end
$var integer 32 '" i [31:0] $end
$upscope $end
$scope task pack_vectors $end
$var integer 32 (" i [31:0] $end
$upscope $end
$scope task set_lane $end
$var reg 4 )" exp_f [3:0] $end
$var reg 3 *" mant_f [2:0] $end
$var reg 1 +" sign $end
$var integer 32 ," idx [31:0] $end
$var integer 32 -" is_weight [31:0] $end
$upscope $end
$upscope $end
$enddefinitions $end
$comment Show the parameter values. $end
$dumpall
b1 n
b0 m
b11 l
b10 k
b1 j
b0 i
b1000 h
b111 g
b110 f
b101 e
b100 d
b11 c
b10 b
b1 a
b0 `
b1000 H
b111 G
b110 F
b101 E
b100 D
b11 C
b10 B
b1 A
b0 @
$end
#0
$dumpvars
bx -"
bx ,"
x+"
bx *"
bx )"
bx ("
bx '"
x&"
bx %"
bx $"
bx #"
bx ""
bx !"
x~
x}
bx |
bx {
bx z
bx y
bx x
bx w
bx v
bx u
bx t
bx s
b1001 r
bx q
bx p
bx o
b1 _
b1 ^
bx ]
bx \
bx [
b0 Z
b0 Y
b0 X
b1 W
b1 V
b0 U
b1001 T
b0 S
b0 R
b0 Q
b0 P
b0 O
b1001 N
b0 M
b0 L
b0 K
b0 J
b0 I
b1001 ?
b0 >
b0 =
b0 <
b0 ;
b0 :
b0 9
b0 8
b0 7
b0 6
b111101100 5
bx 4
b0 3
b0 2
bx 1
bx 0
bx /
bx .
x-
b0 ,
bx +
b0 *
bx )
b0 (
0'
1&
b0 %
b0 $
0#
b111101100 "
bx !
$end
#5000
b0 !
b0 4
b0 ]
b0 [
b0 \
1#
#10000
0#
#15000
1#
#20000
0#
#25000
0&
1#
#30000
0#
#35000
b111101100 o
b0 p
b111101100 y
b0 z
b0 ""
b0 {
b0 |
b0 #"
b0 $"
b0 w
0}
b0 x
0~
b0 %"
b0 s
b0 t
b1001 !"
b0 u
b0 v
b1001 ("
b1 ,
b10000010110110001101100001000000111101001100101011100100110111101110011 q
b1001 r
1#
#40000
1&
0#
#45000
1#
#50000
1'
0&
0#
#55000
1#
#60000
b1 *
0'
0#
#65000
b100010001000100010001000100010001000 8
b100010001000100010001000100010001000 X
b100010001000100010001000100010001000 ;
b100010001000100010001000100010001000 U
b1000 <
b1000 =
b111111111000000000000000000000000000 :
b111111111000000000000000000000000000 J
b1000 M
b111 7
b111 K
b1001 N
b111111111000000000000000000000000000 9
b111111111000000000000000000000000000 P
b1000 S
b111111010 "
b111111010 5
b111 6
b111 Q
b1001 T
b1001 ?
b111111010 o
b1001000000 p
b111111010 y
b1001000000 z
b1001000000 %"
b1000000 ""
b1000 {
b1000 |
b1000 w
b1000 x
b111 u
b111 v
b111 s
b111 t
b1001 !"
b1110000011100000111000001110000011100000111000001110000011100000111000 %
b1110000011100000111000001110000011100000111000001110000011100000111000 3
b1110000011100000111000001110000011100000111000001110000011100000111000 I
b1110000011100000111000001110000011100000111000001110000011100000111000 $
b1110000011100000111000001110000011100000111000001110000011100000111000 2
b1110000011100000111000001110000011100000111000001110000011100000111000 O
b1001 ("
b10 ,
b10000010110110001101100001000000111000001101111011100110110100101110100011010010111011001100101001000000110010101110001011101010110000101101100001000000111011001100001011011000111010101100101 q
b0 *"
b111 )"
0+"
b1000 ,"
b1 -"
b1001 )
1#
#70000
1&
0#
#75000
1#
#80000
1'
0&
0#
#85000
b1001000000 !
b1001000000 4
b1001000000 ]
b1001000000 [
b1001000000 \
1#
#90000
b10 *
0'
0#
#95000
b1001 N
b111111010 "
b111111010 5
b111 7
b111 K
b111111111 >
b111111111 Z
b1001 ?
b111111111110111000000 p
b111111111110111000000 z
1}
b11111111111111111111110111000000 %"
b1001 !"
b111 u
b111 v
b101110001011100010111000101110001011100010111000101110001011100010111000 %
b101110001011100010111000101110001011100010111000101110001011100010111000 3
b101110001011100010111000101110001011100010111000101110001011100010111000 I
b1001 ("
b11 ,
b1000001011011000110110000100000011100000110111101110011011010010111010001101001011101100110010100100000011000010110001101110100001011000010000001100001011011000110110000100000011011100110010101100111011000010111010001101001011101100110010100100000011101110110010101101001011001110110100001110100 q
1+"
b1000 ,"
b1 -"
b1001 )
1#
#100000
1&
0#
#105000
b0 !
b0 4
b0 ]
b0 [
b0 \
1#
#110000
1'
0&
0#
#115000
b111111111110111000000 !
b111111111110111000000 4
b111111111110111000000 ]
b11111111111110111000000 [
b11110111000000 \
1#
#120000
b11 *
0'
0#
#125000
b101110111011101110111011101110111011 8
b101110111011101110111011101110111011 X
b101110111011101110111011101110111011 ;
b101110111011101110111011101110111011 U
b1011 <
b1011 =
b111111111000000000111111111111111111 :
b111111111000000000111111111111111111 J
b1011 M
b1001 N
b111 7
b111 K
b111111111000000000111111111111111111 9
b111111111000000000111111111111111111 P
b1011 S
b1001 T
b111111010 "
b111111010 5
b111 6
b111 Q
b0 >
b0 Z
b1001 ?
b10001000001 p
b10001000001 z
b1111001 ""
b1011 {
b1011 |
b1011 w
b1011 x
1~
b10001000001 %"
b1001 !"
b111 u
b111 v
b101110111011101110111011101110111011101110111011101110111011101110111011 %
b101110111011101110111011101110111011101110111011101110111011101110111011 3
b101110111011101110111011101110111011101110111011101110111011101110111011 I
b101110111011101110111011101110111011101110111011101110111011101110111011 $
b101110111011101110111011101110111011101110111011101110111011101110111011 2
b101110111011101110111011101110111011101110111011101110111011101110111011 O
b1001 ("
b100 ,
b1000010011011110111010001101000001000000110111001100101011001110110000101110100011010010111011001100101001000000010100001110011011010010110011101101110011100110010000001100011011000010110111001100011011001010110110000101001 q
b11 *"
b1000 ,"
b1 -"
b1001 )
1#
#130000
1&
0#
#135000
b0 !
b0 4
b0 ]
b0 [
b0 \
1#
#140000
1'
0&
0#
#145000
b10001000001 !
b10001000001 4
b10001000001 ]
b10001000001 [
b10001000001 \
1#
#150000
b100 *
0'
0#
#155000
b110111011101110111011101110111011101 8
b110111011101110111011101110111011101 X
b101010101010101010101010101010101010 ;
b101010101010101010101010101010101010 U
b1101 <
b1010 =
b111111111111111111000000000111111111 :
b111111111111111111000000000111111111 J
b1101 M
b1001 N
b1001 7
b1001 K
b111111111000000000111111111000000000 9
b111111111000000000111111111000000000 P
b1010 S
b1001 T
b111111110 "
b111111110 5
b1001 6
b1001 Q
b10101010 >
b10101010 Z
b1001 ?
b111111110 o
b10000010 p
b111111110 y
b10000010 z
b10000010 ""
b1101 {
b1010 |
b1101 w
0}
b1010 x
0~
b10000010 %"
b1001 s
b1001 t
b1001 !"
b1001 u
b1001 v
b10011010100110101001101010011010100110101001101010011010100110101001101 %
b10011010100110101001101010011010100110101001101010011010100110101001101 3
b10011010100110101001101010011010100110101001101010011010100110101001101 I
b10010101100101001001010110010100100101011001010010010101100101001001010 $
b10010101100101001001010110010100100101011001010010010101100101001001010 2
b10010101100101001001010110010100100101011001010010010101100101001001010 O
b1001 ("
b101 ,
b10000010110110001110100011001010111001001101110011000010111010001101001011011100110011100100000011000010110001101110100011010010111011001100001011101000110100101101111011011100010000001110011011010010110011101101110 q
b101 *"
b1001 )"
0+"
b1000 ,"
b1 -"
b1001 )
1#
#160000
1&
0#
#165000
b0 !
b0 4
b0 ]
b0 [
b0 \
1#
#170000
1'
0&
0#
